pytakes/__init__.py
pytakes/automate_run.py
pytakes/build_dictionary.py
pytakes/corpus.py
pytakes/header.py
pytakes/negex_creator.py
pytakes/parser.py
pytakes/postprocessor.py
pytakes/processor.py
pytakes/sendmail.py
pytakes/templates.py
pytakes/dict/__init__.py
pytakes/dict/rules.py
pytakes/dict/textitem.py
pytakes/iolib/__init__.py
pytakes/iolib/base.py
pytakes/iolib/config.py
pytakes/iolib/csv.py
pytakes/iolib/jsonl.py
pytakes/iolib/sas.py
pytakes/iolib/sql.py
pytakes/iolib/sqlai.py
pytakes/iolib/templates.py
pytakes/iolib/txt.py
pytakes/nlp/__init__.py
pytakes/nlp/collections.py
pytakes/nlp/conceptminer.py
pytakes/nlp/convert.py
pytakes/nlp/miner.py
pytakes/nlp/ngrams.py
pytakes/nlp/sentence_boundary.py
pytakes/nlp/statusminer.py
pytakes/nlp/terms.py
pytakes/nlp/utils.py
pytakes/nlp/data/ssplit.db
pytakes/nlp/data/status.db
pytakes/run/__init__.py
pytakes/run/runner.py
pytakes/run/schema.py
pytakes/run/simple_run.py
pytakes/util/__init__.py
pytakes/util/db_reader.py
pytakes/util/email_utils.py
pytakes/util/mylogger.py
pytakes/util/utils.py
pytakes-2.0.0.dist-info/entry_points.txt
pytakes-2.0.0.dist-info/LICENSE.txt
pytakes-2.0.0.dist-info/WHEEL
pytakes-2.0.0.dist-info/METADATA
pytakes-2.0.0.dist-info/RECORD
