Metadata-Version: 2.1
Name: pytakes
Version: 2.0.0
Summary: Simple entity extraction module from a lexicon.
Keywords: nlp,information extraction
Author-email: dcronkite <dcronkite+pypi@gmail.com>
Requires-Python: >=3.8
Classifier: Development Status :: 5 - Production/Stable
Classifier: Intended Audience :: Science/Research
Classifier: Programming Language :: Python :: 3 :: Only
Classifier: Programming Language :: Python :: 3.8
Classifier: Programming Language :: Python :: 3.9
Classifier: Programming Language :: Python :: 3.10
Classifier: Programming Language :: Python :: 3.11
Classifier: Programming Language :: Python :: 3.12
Classifier: Topic :: Text Processing :: Linguistic
Classifier: License :: OSI Approved :: MIT License
Classifier: Intended Audience :: Healthcare Industry
Requires-Dist: regex
Requires-Dist: jinja2
Requires-Dist: pyodbc
Requires-Dist: sqlalchemy
Requires-Dist: jsonschema
Requires-Dist: pyyaml
Requires-Dist: loguru
Requires-Dist: pyodbc ; extra == "db"
Requires-Dist: pytest ; extra == "dev"
Requires-Dist: psycopg2 ; extra == "postgres"
Requires-Dist: sas7bdat ; extra == "sas"
Project-URL: Home, https://github.com/dcronkite/pytakes
Provides-Extra: db
Provides-Extra: dev
Provides-Extra: postgres
Provides-Extra: sas
